pydantic_compat/__init__.py
pydantic_compat/_shared.py
pydantic_compat/py.typed
pydantic_compat/v1.py
pydantic_compat/_v1/__init__.py
pydantic_compat/_v1/decorators.py
pydantic_compat/_v1/mixin.py
pydantic_compat/_v2/__init__.py
pydantic_compat/_v2/decorators.py
pydantic_compat/_v2/mixin.py
pydantic_compat-0.1.1.dist-info/METADATA
pydantic_compat-0.1.1.dist-info/WHEEL
pydantic_compat-0.1.1.dist-info/licenses/LICENSE
pydantic_compat-0.1.1.dist-info/RECORD
