Metadata-Version: 2.1
Name: pydantic-compat
Version: 0.1.1
Summary: Compatibility layer for pydantic v1/v2
Project-URL: homepage, https://github.com/pyapp-kit/pydantic-compat
Project-URL: repository, https://github.com/pyapp-kit/pydantic-compat
Author-email: Talley Lambert <talley.lambert@gmail.com>
License: BSD 3-Clause License
License-File: LICENSE
Classifier: Development Status :: 3 - Alpha
Classifier: Framework :: Pydantic
Classifier: License :: OSI Approved :: BSD License
Classifier: Natural Language :: English
Classifier: Programming Language :: Python :: 3
Classifier: Programming Language :: Python :: 3.7
Classifier: Programming Language :: Python :: 3.8
Classifier: Programming Language :: Python :: 3.9
Classifier: Programming Language :: Python :: 3.10
Classifier: Programming Language :: Python :: 3.11
Classifier: Programming Language :: Python :: 3.12
Classifier: Typing :: Typed
Requires-Python: >=3.7
Requires-Dist: importlib-metadata; python_version < '3.8'
Requires-Dist: pydantic
Provides-Extra: dev
Requires-Dist: black; extra == 'dev'
Requires-Dist: ipython; extra == 'dev'
Requires-Dist: mypy; extra == 'dev'
Requires-Dist: pdbpp; extra == 'dev'
Requires-Dist: pre-commit; extra == 'dev'
Requires-Dist: pytest; extra == 'dev'
Requires-Dist: pytest-cov; extra == 'dev'
Requires-Dist: rich; extra == 'dev'
Requires-Dist: ruff; extra == 'dev'
Provides-Extra: test
Requires-Dist: pytest-cov; extra == 'test'
Requires-Dist: pytest>=6.0; extra == 'test'
